pydistcheck/__init__.py
pydistcheck/_checks.py
pydistcheck/_compat.py
pydistcheck/_config.py
pydistcheck/_distribution_summary.py
pydistcheck/_file_utils.py
pydistcheck/_inspect.py
pydistcheck/_shared_lib_utils.py
pydistcheck/_utils.py
pydistcheck/cli.py
pydistcheck-0.11.3.dist-info/METADATA
pydistcheck-0.11.3.dist-info/WHEEL
pydistcheck-0.11.3.dist-info/entry_points.txt
pydistcheck-0.11.3.dist-info/licenses/LICENSE
pydistcheck-0.11.3.dist-info/licenses/LICENSES/DELOCATE_LICENSE
pydistcheck-0.11.3.dist-info/RECORD
