Metadata-Version: 2.4
Name: pydistcheck
Version: 0.11.3
Summary: Inspect Python package distributions and raise warnings on common problems.
Project-URL: homepage, https://pydistcheck.readthedocs.io/en/latest/
Project-URL: documentation, https://pydistcheck.readthedocs.io/en/latest/
Project-URL: repository, https://github.com/jameslamb/pydistcheck
Project-URL: changelog, https://github.com/jameslamb/pydistcheck/releases
Author-email: James Lamb <jaylamb20@gmail.com>
Maintainer-email: James Lamb <jaylamb20@gmail.com>
License-Expression: BSD-3-Clause
License-File: LICENSE
License-File: LICENSES/DELOCATE_LICENSE
Keywords: linter,python-packaging,testing
Classifier: Development Status :: 4 - Beta
Classifier: Intended Audience :: Developers
Classifier: Operating System :: MacOS
Classifier: Operating System :: Microsoft :: Windows
Classifier: Operating System :: POSIX
Classifier: Operating System :: Unix
Classifier: Programming Language :: Python
Classifier: Programming Language :: Python :: 3
Classifier: Programming Language :: Python :: 3 :: Only
Classifier: Programming Language :: Python :: 3.9
Classifier: Programming Language :: Python :: 3.10
Classifier: Programming Language :: Python :: 3.11
Classifier: Programming Language :: Python :: 3.12
Classifier: Programming Language :: Python :: 3.13
Classifier: Programming Language :: Python :: 3.14
Classifier: Programming Language :: Python :: Implementation :: CPython
Classifier: Programming Language :: Python :: Implementation :: PyPy
Classifier: Topic :: Software Development
Classifier: Topic :: Utilities
Requires-Python: >=3.9
Requires-Dist: click>=8.0
Requires-Dist: tomli>=1.1.0; python_version < '3.11'
Provides-Extra: conda
Requires-Dist: zstandard>=0.22.0; (python_version < '3.14') and extra == 'conda'
